retrodevem/1khz_square.py
retrodevem/__init__.py
retrodevem/atarist_joystick.py
retrodevem/atarist_mouse.py
retrodevem/inputdevice.py
retrodevem-0.9.dist-info/METADATA
retrodevem-0.9.dist-info/WHEEL
retrodevem-0.9.dist-info/entry_points.txt
retrodevem-0.9.dist-info/licenses/LICENSE
retrodevem-0.9.dist-info/RECORD
