Metadata-Version: 2.4
Name: retrodevem
Version: 0.9
Summary: RetroDevEm (Retro Device Emulator) is a free (as in Free Software) input devices (mouse and joystick) emulator for retro consoles and computers (Atari 2600, Atari ST, Amstrad CPC, ...).
Project-URL: Homepage, https://github.com/FlorentFlament/RetroDevEm
Project-URL: Issues, https://github.com/FlorentFlament/RetroDevEm/issues
Author-email: Florent Flament <contact@florentflament.com>
License-File: LICENSE
Keywords: Amstrad CPC,Atari 2600,Atari ST,USB,gamepad,joystick,mouse,retrocomputing,retrogaming
Classifier: License :: OSI Approved :: GNU General Public License v3 (GPLv3)
Classifier: Operating System :: POSIX :: Linux
Classifier: Programming Language :: Python :: 3
Requires-Python: >=3
Requires-Dist: click
Requires-Dist: gpiozero
Requires-Dist: lgpio
